FindYourProfessor/__init__.py
FindYourProfessor/scraper.py
FindYourProfessor-0.2.dist-info/LICENSE.md
FindYourProfessor-0.2.dist-info/METADATA
FindYourProfessor-0.2.dist-info/WHEEL
FindYourProfessor-0.2.dist-info/entry_points.txt
FindYourProfessor-0.2.dist-info/top_level.txt
FindYourProfessor-0.2.dist-info/RECORD
